README.md
setup.cfg
setup.py
bmdistributions/Binomialdistribution.py
bmdistributions/Gaussiandistribution.py
bmdistributions/Generaldistribution.py
bmdistributions/__init__.py
bmdistributions.egg-info/PKG-INFO
bmdistributions.egg-info/SOURCES.txt
bmdistributions.egg-info/dependency_links.txt
bmdistributions.egg-info/not-zip-safe
bmdistributions.egg-info/top_level.txt